{"fixtures": [{"code": 1059965, "team_h": 7, "team_h_score": null, "team_a": 13, "team_a_score": null, "event": 27, "finished": false, "minutes": 0, "provisional_start_time": false, "kickoff_time": "2020-02-22T15:00:00Z", "event_name": "Gameweek 27", "is_home": true, "difficulty": 2}, {"code": 1059974, "team_h": 4, "team_h_score": null, "team_a": 7, "team_a_score": null, "event": 28, "finished": false, "minutes": 0, "provisional_start_time": false, "kickoff_time": "2020-02-29T12:30:00Z", "event_name": "Gameweek 28", "is_home": false, "difficulty": 3}, {"code": 1059985, "team_h": 7, "team_h_score": null, "team_a": 18, "team_a_score": null, "event": 29, "finished": false, "minutes": 0, "provisional_start_time": false, "kickoff_time": "2020-03-07T15:00:00Z", "event_name": "Gameweek 29", "is_home": true, "difficulty": 2}, {"code": 1059992, "team_h": 3, "team_h_score": null, "team_a": 7, "team_a_score": null, "event": 30, "finished": false, "minutes": 0, "provisional_start_time": false, "kickoff_time": "2020-03-14T15:00:00Z", "event_name": "Gameweek 30", "is_home": false, "difficulty": 3}, {"code": 1060005, "team_h": 10, "team_h_score": null, "team_a": 7, "team_a_score": null, "event": 31, "finished": false, "minutes": 0, "provisional_start_time": false, "kickoff_time": "2020-03-21T17:30:00Z", "event_name": "Gameweek 31", "is_home": false, "difficulty": 5}, {"code": 1060016, "team_h": 7, "team_h_score": null, "team_a": 5, "team_a_score": null, "event": 32, "finished": false, "minutes": 0, "provisional_start_time": false, "kickoff_time": "2020-04-04T14:00:00Z", "event_name": "Gameweek 32", "is_home": true, "difficulty": 2}, {"code": 1060024, "team_h": 9, "team_h_score": null, "team_a": 7, "team_a_score": null, "event": 33, "finished": false, "minutes": 0, "provisional_start_time": false, "kickoff_time": "2020-04-11T14:00:00Z", "event_name": "Gameweek 33", "is_home": false, "difficulty": 4}, {"code": 1060036, "team_h": 7, "team_h_score": null, "team_a": 6, "team_a_score": null, "event": 34, "finished": false, "minutes": 0, "provisional_start_time": false, "kickoff_time": "2020-04-18T14:00:00Z", "event_name": "Gameweek 34", "is_home": true, "difficulty": 4}, {"code": 1060043, "team_h": 2, "team_h_score": null, "team_a": 7, "team_a_score": null, "event": 35, "finished": false, "minutes": 0, "provisional_start_time": false, "kickoff_time": "2020-04-25T14:00:00Z", "event_name": "Gameweek 35", "is_home": false, "difficulty": 2}, {"code": 1060055, "team_h": 7, "team_h_score": null, "team_a": 12, "team_a_score": null, "event": 36, "finished": false, "minutes": 0, "provisional_start_time": false, "kickoff_time": "2020-05-02T14:00:00Z", "event_name": "Gameweek 36", "is_home": true, "difficulty": 4}, {"code": 1060071, "team_h": 20, "team_h_score": null, "team_a": 7, "team_a_score": null, "event": 37, "finished": false, "minutes": 0, "provisional_start_time": false, "kickoff_time": "2020-05-09T14:00:00Z", "event_name": "Gameweek 37", "is_home": false, "difficulty": 3}, {"code": 1060075, "team_h": 7, "team_h_score": null, "team_a": 17, "team_a_score": null, "event": 38, "finished": false, "minutes": 0, "provisional_start_time": false, "kickoff_time": "2020-05-17T14:00:00Z", "event_name": "Gameweek 38", "is_home": true, "difficulty": 4}], "history": [{"element": 608, "fixture": 225, "opponent_team": 11, "total_points": 0, "was_home": false, "kickoff_time": "2020-01-18T15:00:00Z", "team_h_score": 2, "team_a_score": 2, "round": 23, "minutes": 0, "goals_scored": 0, "assists": 0, "clean_sheets": 0, "goals_conceded": 0, "own_goals": 0, "penalties_saved": 0, "penalties_missed": 0, "yellow_cards": 0, "red_cards": 0, "saves": 0, "bonus": 0, "bps": 0, "influence": "0.0", "creativity": "0.0", "threat": "0.0", "ict_index": "0.0", "value": 45, "transfers_balance": 0, "selected": 0, "transfers_in": 0, "transfers_out": 0}, {"element": 608, "fixture": 239, "opponent_team": 16, "total_points": 0, "was_home": true, "kickoff_time": "2020-01-21T19:30:00Z", "team_h_score": 0, "team_a_score": 2, "round": 24, "minutes": 0, "goals_scored": 0, "assists": 0, "clean_sheets": 0, "goals_conceded": 0, "own_goals": 0, "penalties_saved": 0, "penalties_missed": 0, "yellow_cards": 0, "red_cards": 0, "saves": 0, "bonus": 0, "bps": 0, "influence": "0.0", "creativity": "0.0", "threat": "0.0", "ict_index": "0.0", "value": 45, "transfers_balance": 25, "selected": 48, "transfers_in": 33, "transfers_out": 8}, {"element": 608, "fixture": 243, "opponent_team": 15, "total_points": 0, "was_home": true, "kickoff_time": "2020-02-01T15:00:00Z", "team_h_score": 0, "team_a_score": 1, "round": 25, "minutes": 0, "goals_scored": 0, "assists": 0, "clean_sheets": 0, "goals_conceded": 0, "own_goals": 0, "penalties_saved": 0, "penalties_missed": 0, "yellow_cards": 0, "red_cards": 0, "saves": 0, "bonus": 0, "bps": 0, "influence": "0.0", "creativity": "0.0", "threat": "0.0", "ict_index": "0.0", "value": 45, "transfers_balance": 21, "selected": 92, "transfers_in": 39, "transfers_out": 18}, {"element": 608, "fixture": 255, "opponent_team": 8, "total_points": 0, "was_home": false, "kickoff_time": "2020-02-08T12:30:00Z", "team_h_score": 3, "team_a_score": 1, "round": 26, "minutes": 0, "goals_scored": 0, "assists": 0, "clean_sheets": 0, "goals_conceded": 0, "own_goals": 0, "penalties_saved": 0, "penalties_missed": 0, "yellow_cards": 0, "red_cards": 0, "saves": 0, "bonus": 0, "bps": 0, "influence": "0.0", "creativity": "0.0", "threat": "0.0", "ict_index": "0.0", "value": 45, "transfers_balance": 7, "selected": 99, "transfers_in": 39, "transfers_out": 32}], "history_past": []}