{"fixtures": [{"code": 1059967, "team_h": 10, "team_h_score": null, "team_a": 19, "team_a_score": null, "event": 27, "finished": false, "minutes": 0, "provisional_start_time": false, "kickoff_time": "2020-02-24T20:00:00Z", "event_name": "Gameweek 27", "is_home": false, "difficulty": 5}, {"code": 1059981, "team_h": 19, "team_h_score": null, "team_a": 16, "team_a_score": null, "event": 28, "finished": false, "minutes": 0, "provisional_start_time": false, "kickoff_time": "2020-02-29T15:00:00Z", "event_name": "Gameweek 28", "is_home": true, "difficulty": 2}, {"code": 1059982, "team_h": 1, "team_h_score": null, "team_a": 19, "team_a_score": null, "event": 29, "finished": false, "minutes": 0, "provisional_start_time": false, "kickoff_time": "2020-03-07T15:00:00Z", "event_name": "Gameweek 29", "is_home": false, "difficulty": 4}, {"code": 1060001, "team_h": 19, "team_h_score": null, "team_a": 20, "team_a_score": null, "event": 30, "finished": false, "minutes": 0, "provisional_start_time": false, "kickoff_time": "2020-03-15T14:00:00Z", "event_name": "Gameweek 30", "is_home": true, "difficulty": 3}, {"code": 1060010, "team_h": 17, "team_h_score": null, "team_a": 19, "team_a_score": null, "event": 31, "finished": false, "minutes": 0, "provisional_start_time": false, "kickoff_time": "2020-03-20T20:00:00Z", "event_name": "Gameweek 31", "is_home": false, "difficulty": 4}, {"code": 1060021, "team_h": 19, "team_h_score": null, "team_a": 6, "team_a_score": null, "event": 32, "finished": false, "minutes": 0, "provisional_start_time": false, "kickoff_time": "2020-04-05T13:00:00Z", "event_name": "Gameweek 32", "is_home": true, "difficulty": 4}, {"code": 1060027, "team_h": 13, "team_h_score": null, "team_a": 19, "team_a_score": null, "event": 33, "finished": false, "minutes": 0, "provisional_start_time": false, "kickoff_time": "2020-04-11T14:00:00Z", "event_name": "Gameweek 33", "is_home": false, "difficulty": 3}, {"code": 1060041, "team_h": 19, "team_h_score": null, "team_a": 5, "team_a_score": null, "event": 34, "finished": false, "minutes": 0, "provisional_start_time": false, "kickoff_time": "2020-04-18T14:00:00Z", "event_name": "Gameweek 34", "is_home": true, "difficulty": 2}, {"code": 1060047, "team_h": 14, "team_h_score": null, "team_a": 19, "team_a_score": null, "event": 35, "finished": false, "minutes": 0, "provisional_start_time": false, "kickoff_time": "2020-04-25T14:00:00Z", "event_name": "Gameweek 35", "is_home": false, "difficulty": 2}, {"code": 1060061, "team_h": 19, "team_h_score": null, "team_a": 18, "team_a_score": null, "event": 36, "finished": false, "minutes": 0, "provisional_start_time": false, "kickoff_time": "2020-05-02T14:00:00Z", "event_name": "Gameweek 36", "is_home": true, "difficulty": 2}, {"code": 1060066, "team_h": 12, "team_h_score": null, "team_a": 19, "team_a_score": null, "event": 37, "finished": false, "minutes": 0, "provisional_start_time": false, "kickoff_time": "2020-05-09T14:00:00Z", "event_name": "Gameweek 37", "is_home": false, "difficulty": 4}, {"code": 1060081, "team_h": 19, "team_h_score": null, "team_a": 2, "team_a_score": null, "event": 38, "finished": false, "minutes": 0, "provisional_start_time": false, "kickoff_time": "2020-05-17T14:00:00Z", "event_name": "Gameweek 38", "is_home": true, "difficulty": 2}], "history": [{"element": 616, "fixture": 250, "opponent_team": 4, "total_points": 2, "was_home": true, "kickoff_time": "2020-02-01T15:00:00Z", "team_h_score": 3, "team_a_score": 3, "round": 25, "minutes": 84, "goals_scored": 0, "assists": 0, "clean_sheets": 0, "goals_conceded": 3, "own_goals": 0, "penalties_saved": 0, "penalties_missed": 0, "yellow_cards": 0, "red_cards": 0, "saves": 0, "bonus": 0, "bps": 7, "influence": "21.6", "creativity": "12.0", "threat": "39.0", "ict_index": "7.3", "value": 50, "transfers_balance": 466, "selected": 488, "transfers_in": 501, "transfers_out": 35}, {"element": 616, "fixture": 256, "opponent_team": 11, "total_points": 2, "was_home": false, "kickoff_time": "2020-02-19T19:30:00Z", "team_h_score": 2, "team_a_score": 0, "round": 26, "minutes": 90, "goals_scored": 0, "assists": 0, "clean_sheets": 0, "goals_conceded": 2, "own_goals": 0, "penalties_saved": 0, "penalties_missed": 0, "yellow_cards": 0, "red_cards": 0, "saves": 0, "bonus": 0, "bps": 11, "influence": "15.4", "creativity": "0.9", "threat": "2.0", "ict_index": "1.8", "value": 50, "transfers_balance": 370, "selected": 884, "transfers_in": 457, "transfers_out": 87}, {"element": 616, "fixture": 266, "opponent_team": 10, "total_points": 0, "was_home": false, "kickoff_time": "2020-02-24T20:00:00Z", "team_h_score": null, "team_a_score": null, "round": 27, "minutes": 0, "goals_scored": 0, "assists": 0, "clean_sheets": 0, "goals_conceded": 0, "own_goals": 0, "penalties_saved": 0, "penalties_missed": 0, "yellow_cards": 0, "red_cards": 0, "saves": 0, "bonus": 0, "bps": 0, "influence": "0.0", "creativity": "0.0", "threat": "0.0", "ict_index": "0.0", "value": 50, "transfers_balance": 17, "selected": 937, "transfers_in": 103, "transfers_out": 86}], "history_past": []}